PeerMark/__init__.py
PeerMark/_version.py
PeerMark/extract_peer.py
PeerMark/generate_peer_review.py
PeerMark/data/__init__.py
PeerMark/data/team_of_3.xlsx
PeerMark/data/team_of_4.xlsx
PeerMark/data/team_of_5.xlsx
peermark-0.7.dist-info/COPYING
peermark-0.7.dist-info/METADATA
peermark-0.7.dist-info/WHEEL
peermark-0.7.dist-info/entry_points.txt
peermark-0.7.dist-info/top_level.txt
peermark-0.7.dist-info/RECORD
